src/__init__.py
src/byte_operators.py
src/common.py
src/grid.py
src/individual.py
src/optimizer.py
src/population.py
src/benchmark/__init__.py
src/benchmark/JSSP/6J-2M.txt
src/benchmark/JSSP/__init__.py
src/example/__init__.py
src/example/deneme.py
src/example/example_cellukeyga.py
src/example/example_cga.py
src/mutation/__init__.py
src/mutation/bit_flip_mutation.py
src/mutation/byte_mutation.py
src/mutation/byte_mutation_random.py
src/mutation/float_uniform_mutation.py
src/mutation/insertion_mutation.py
src/mutation/mutation_operator.py
src/mutation/shuffle_mutation.py
src/mutation/swap_mutation.py
src/mutation/two_opt_mutation.py
src/neighborhoods/__init__.py
src/neighborhoods/compact_13.py
src/neighborhoods/compact_21.py
src/neighborhoods/compact_25.py
src/neighborhoods/compact_9.py
src/neighborhoods/linear_5.py
src/neighborhoods/linear_9.py
src/problem/__init__.py
src/problem/abstract_problem.py
src/problem/job_shop.py
src/problem/job_shop_cellukeyga.py
src/problem/tsp.py
src/problem/tsp_cellukeyga.py
src/recombination/__init__.py
src/recombination/arithmetic_crossover.py
src/recombination/blxalpha_crossover.py
src/recombination/byte_one_point_crossover.py
src/recombination/byte_uniform_crossover.py
src/recombination/flat_crossover.py
src/recombination/linear_crossover.py
src/recombination/one_point_crossover.py
src/recombination/pmx_crossover.py
src/recombination/recombination_operator.py
src/recombination/two_point_crossover.py
src/recombination/unfair_avarage_crossover.py
src/recombination/uniform_crossover.py
src/selection/__init__.py
src/selection/roulette_wheel_selection.py
src/selection/selection_operator.py
src/selection/tournament_selection_cellukeyga.py
src/selection/tournament_selection_cga.py
src/tests/__init__.py
src/tests/conftest.py
src/tests/noteontests.txt
src/tests/test_pmx_crossover.py
CelluKeyGA-0.1.0.dist-info/LICENSE
CelluKeyGA-0.1.0.dist-info/METADATA
CelluKeyGA-0.1.0.dist-info/WHEEL
CelluKeyGA-0.1.0.dist-info/top_level.txt
CelluKeyGA-0.1.0.dist-info/RECORD
