Metadata-Version: 2.2
Name: CelluKeyGA
Version: 0.1.0
Summary: A Python library that integrates **Cellular Genetic Algorithm (Cellular GA)** with **Biased Random-Key Genetic Algorithm (BRKGA)** to enhance optimization capabilities.
Home-page: https://github.com/SevgiAkten/CelluKeyGA
Author: Sevgi Akten Karakaya, Mehmet Hakan Satman
Author-email: sevgiakten@gmail.com, mhsatman@gmail.com
Project-URL: Documentation, https://sevgiakten.github.io/CelluKeyGA/
Project-URL: Source, https://github.com/SevgiAkten/CelluKeyGA
Project-URL: Issue Tracker, https://github.com/SevgiAkten/CelluKeyGA/issues
Project-URL: PyPI, https://pypi.org/project/CelluKeyGA/
Classifier: Programming Language :: Python :: 3
Classifier: License :: OSI Approved :: MIT License
Classifier: Operating System :: OS Independent
Requires-Python: >=3.6
License-File: LICENSE
Provides-Extra: dev
Requires-Dist: pytest<9.0,>=8.0; extra == "dev"
Requires-Dist: pytest-xdist<4.0,>=3.0; extra == "dev"
Requires-Dist: grip==4.6.2; extra == "dev"
Requires-Dist: Markdown==3.6; extra == "dev"
Requires-Dist: Markdown-Editor==1.0.7; extra == "dev"
Requires-Dist: path-and-address==2.0.1; extra == "dev"
Requires-Dist: pluggy==1.5.0; extra == "dev"
Requires-Dist: six==1.16.0; extra == "dev"
Provides-Extra: docs
Requires-Dist: sphinx<8.0,>=7.4.0; extra == "docs"
Requires-Dist: sphinx-rtd-theme<3.0,>=2.0.0; extra == "docs"
Requires-Dist: sphinxcontrib-applehelp<3.0,>=2.0.0; extra == "docs"
Requires-Dist: sphinxcontrib-htmlhelp<3.0,>=2.1.0; extra == "docs"
Requires-Dist: sphinxcontrib-jquery<5.0,>=4.1; extra == "docs"
Requires-Dist: sphinxcontrib-jsmath<2.0,>=1.0.0; extra == "docs"
Requires-Dist: sphinxcontrib-qthelp<3.0,>=2.0.0; extra == "docs"
Requires-Dist: sphinxcontrib-serializinghtml<3.0,>=2.0.0; extra == "docs"
